demo_eg/README.md
demo_eg/__init__.py
demo_eg/main.py
demo_eg/project.cfg
demo_eg/setting.py
demo_eg/url_source.py
jd_program_temp/__init__.py
jd_program_temp/__version__.py
jd_program_temp/readme.md
jd_program_temp/setting.py
jd_program_temp/commands/__init__.py
jd_program_temp/commands/cmdline.py
jd_program_temp/commands/create_builder.py
jd_program_temp/commands/generate/__init__.py
jd_program_temp/commands/generate/generate_project.py
jd_program_temp/commons/__init__.py
jd_program_temp/commons/common_cfg.py
jd_program_temp/commons/common_fun.py
jd_program_temp/monitor/__init__.py
jd_program_temp/monitor/monitor_decorator.py
jd_program_temp/monitor/monitor_signal_alert.py
jd_program_temp/program_process/__init__.py
jd_program_temp/program_process/process_sftp.py
jd_program_temp/program_process/process_url.py
jd_program_temp/program_process/process_work.py
jd_program_temp/request_downloader/__init__.py
jd_program_temp/request_downloader/downloaders.py
jd_program_temp/templates/__init__.py
jd_program_temp/templates/project_template/README.md
jd_program_temp/templates/project_template/__init__.py
jd_program_temp/templates/project_template/main.py
jd_program_temp/templates/project_template/project.cfg
jd_program_temp/templates/project_template/setting.py
jd_program_temp/templates/project_template/url_source.py
jd_program_temp/utils/__init__.py
jd_program_temp/utils/custom_argparsers.py
jd_program_temp-0.0.1.dist-info/DESCRIPTION.rst
jd_program_temp-0.0.1.dist-info/METADATA
jd_program_temp-0.0.1.dist-info/RECORD
jd_program_temp-0.0.1.dist-info/WHEEL
jd_program_temp-0.0.1.dist-info/entry_points.txt
jd_program_temp-0.0.1.dist-info/metadata.json
jd_program_temp-0.0.1.dist-info/top_level.txt
