Metadata-Version: 2.0
Name: jd-program-temp
Version: 0.0.1
Summary: jinde py program temp
Home-page: UNKNOWN
Author: nico_zhang
Author-email: zhangyf@jindefund.com
License: UNKNOWN
Platform: win_amd64
Classifier: Programming Language :: Python :: 3
Classifier: License :: OSI Approved :: MIT License
Classifier: Operating System :: OS Independent
Requires-Python: >3.5
Requires-Dist: fabric
Requires-Dist: requests
Requires-Dist: cchardet
